README.md
setup.py
exuse/__init__.py
exuse/exargparse.py
exuse/exio.py
exuse/exlogging.py
exuse/expath.py
exuse/exshell.py
exuse/extime.py
exuse/extypings.py
exuse/lodash.py
exuse/subprocess.py
exuse.egg-info/PKG-INFO
exuse.egg-info/SOURCES.txt
exuse.egg-info/dependency_links.txt
exuse.egg-info/top_level.txt
exuse/printutils/__init__.py
exuse/printutils/step.py