Metadata-Version: 1.0
Name: exuse
Version: 0.1.9
Summary: 简单的使用简单的工具
Home-page: UNKNOWN
Author: barwe
Author-email: barwechin@163.com
License: UNKNOWN
Platform: UNKNOWN
